pclink/__init__.py
pclink/__main__.py
pclink/launcher.py
pclink/main.py
pclink/api_server/__init__.py
pclink/api_server/api.py
pclink/api_server/applications_router.py
pclink/api_server/control_api.py
pclink/api_server/discovery.py
pclink/api_server/extension_router.py
pclink/api_server/file_browser.py
pclink/api_server/info_router.py
pclink/api_server/input_router.py
pclink/api_server/macro_router.py
pclink/api_server/media_router.py
pclink/api_server/media_streaming.py
pclink/api_server/process_manager.py
pclink/api_server/services.py
pclink/api_server/system_router.py
pclink/api_server/terminal.py
pclink/api_server/utils_router.py
pclink/api_server/transfers/__init__.py
pclink/api_server/transfers/download.py
pclink/api_server/transfers/models.py
pclink/api_server/transfers/session.py
pclink/api_server/transfers/upload.py
pclink/assets/icon.ico
pclink/assets/icon.png
pclink/assets/icon.svg
pclink/assets/pclink.svg
pclink/assets/pclink_dark.ico
pclink/assets/pclink_dark.png
pclink/assets/pclink_light.ico
pclink/assets/pclink_light.png
pclink/core/__init__.py
pclink/core/config.py
pclink/core/constants.py
pclink/core/controller.py
pclink/core/device_manager.py
pclink/core/exceptions.py
pclink/core/extension_base.py
pclink/core/extension_context.py
pclink/core/extension_manager.py
pclink/core/logging.py
pclink/core/server_controller.py
pclink/core/setup_guide.py
pclink/core/singleton.py
pclink/core/startup.py
pclink/core/state.py
pclink/core/system_tray.py
pclink/core/update_checker.py
pclink/core/utils.py
pclink/core/validators.py
pclink/core/version.py
pclink/core/wayland_utils.py
pclink/core/web_auth.py
pclink/core/windows_console.py
pclink/core/windows_notifier.py
pclink/web_ui/__init__.py
pclink/web_ui/router.py
pclink/web_ui/static/app.js
pclink/web_ui/static/auth.html
pclink/web_ui/static/auth.js
pclink/web_ui/static/extension-theme.js
pclink/web_ui/static/feather.min.js
pclink/web_ui/static/index.html
pclink/web_ui/static/qrcode.min.js
pclink-3.2.0.dist-info/licenses/LICENSE
pclink-3.2.0.dist-info/licenses/LICENSE.AGPL
pclink-3.2.0.dist-info/licenses/NOTICES
pclink-3.2.0.dist-info/METADATA
pclink-3.2.0.dist-info/WHEEL
pclink-3.2.0.dist-info/entry_points.txt
pclink-3.2.0.dist-info/top_level.txt
pclink-3.2.0.dist-info/RECORD
