Metadata-Version: 2.4
Name: pclink
Version: 3.2.0
Summary: Cross-platform desktop app for secure remote PC control and management, featuring a lightweight built-in WebUI and API for local or remote access.
Author-email: AZHAR ZOUHIR <azhar@bytedz.xyz>
License-Expression: AGPL-3.0-or-later
Project-URL: Homepage, https://github.com/BYTEDz/PCLink
Project-URL: Repository, https://github.com/BYTEDz/PCLink
Project-URL: Issues, https://github.com/BYTEDz/PCLink/issues
Classifier: Development Status :: 4 - Beta
Classifier: Intended Audience :: End Users/Desktop
Classifier: Programming Language :: Python :: 3
Classifier: Programming Language :: Python :: 3.8
Classifier: Programming Language :: Python :: 3.9
Classifier: Programming Language :: Python :: 3.10
Classifier: Programming Language :: Python :: 3.11
Requires-Python: >=3.8
License-File: LICENSE
License-File: LICENSE.AGPL
License-File: NOTICES
Requires-Dist: fastapi>=0.95.0
Requires-Dist: uvicorn[standard]>=0.22.0
Requires-Dist: websockets>=12.0
Requires-Dist: wsproto>=1.2.0
Requires-Dist: psutil>=5.9.0
Requires-Dist: pyperclip>=1.8.2
Requires-Dist: mss>=9.0.0
Requires-Dist: keyboard>=0.13.5
Requires-Dist: requests>=2.31.0
Requires-Dist: cryptography>=41.0.0
Requires-Dist: getmac>=0.9.0
Requires-Dist: pyautogui>=0.9.54
Requires-Dist: pynput>=1.7.6
Requires-Dist: packaging>=21.0
Requires-Dist: PyYAML>=6.0.0
Requires-Dist: click
Requires-Dist: qrcode>=7.3
Requires-Dist: aiofiles>=23.0.0
Requires-Dist: Pillow>=9.0.0
Requires-Dist: pystray>=0.19.0
Requires-Dist: python-multipart>=0.0.9
Requires-Dist: comtypes>=1.2.0; sys_platform == "win32"
Requires-Dist: pycaw>=20230330; sys_platform == "win32"
Requires-Dist: pywin32>=306; sys_platform == "win32"
Requires-Dist: winsdk>=1.0.0b9; sys_platform == "win32"
Provides-Extra: dev
Requires-Dist: pytest>=7.3.1; extra == "dev"
Requires-Dist: pytest-cov>=4.1.0; extra == "dev"
Requires-Dist: black>=23.3.0; extra == "dev"
Requires-Dist: isort>=5.12.0; extra == "dev"
Requires-Dist: flake8>=6.0.0; extra == "dev"
Requires-Dist: mypy>=1.3.0; extra == "dev"
Requires-Dist: pyinstaller>=5.13.0; extra == "dev"
Requires-Dist: pre-commit>=2.0; extra == "dev"
Requires-Dist: build; extra == "dev"
Requires-Dist: svglib>=1.5.1; extra == "dev"
Requires-Dist: reportlab>=4.0.0; extra == "dev"
Dynamic: license-file
